tinkoff/invest/__init__.py
tinkoff/invest/_errors.py
tinkoff/invest/_grpc_helpers.py
tinkoff/invest/async_services.py
tinkoff/invest/caching/__init__.py
tinkoff/invest/caching/instruments_cache/__init__.py
tinkoff/invest/caching/instruments_cache/instrument_storage.py
tinkoff/invest/caching/instruments_cache/instruments_cache.py
tinkoff/invest/caching/instruments_cache/interface.py
tinkoff/invest/caching/instruments_cache/models.py
tinkoff/invest/caching/instruments_cache/protocol.py
tinkoff/invest/caching/instruments_cache/settings.py
tinkoff/invest/caching/market_data_cache/__init__.py
tinkoff/invest/caching/market_data_cache/cache.py
tinkoff/invest/caching/market_data_cache/cache_settings.py
tinkoff/invest/caching/market_data_cache/datetime_range.py
tinkoff/invest/caching/market_data_cache/instrument_date_range_market_data.py
tinkoff/invest/caching/market_data_cache/instrument_market_data_storage.py
tinkoff/invest/caching/market_data_cache/interface.py
tinkoff/invest/caching/market_data_cache/serialization.py
tinkoff/invest/caching/overrides.py
tinkoff/invest/candle_getter_protocol.py
tinkoff/invest/channels.py
tinkoff/invest/clients.py
tinkoff/invest/constants.py
tinkoff/invest/exceptions.py
tinkoff/invest/grpc/__init__.py
tinkoff/invest/grpc/common_pb2.py
tinkoff/invest/grpc/common_pb2.pyi
tinkoff/invest/grpc/common_pb2_grpc.py
tinkoff/invest/grpc/google/api/field_behavior_pb2.py
tinkoff/invest/grpc/google/api/field_behavior_pb2.pyi
tinkoff/invest/grpc/google/api/field_behavior_pb2_grpc.py
tinkoff/invest/grpc/instruments_pb2.py
tinkoff/invest/grpc/instruments_pb2.pyi
tinkoff/invest/grpc/instruments_pb2_grpc.py
tinkoff/invest/grpc/marketdata_pb2.py
tinkoff/invest/grpc/marketdata_pb2.pyi
tinkoff/invest/grpc/marketdata_pb2_grpc.py
tinkoff/invest/grpc/operations_pb2.py
tinkoff/invest/grpc/operations_pb2.pyi
tinkoff/invest/grpc/operations_pb2_grpc.py
tinkoff/invest/grpc/orders_pb2.py
tinkoff/invest/grpc/orders_pb2.pyi
tinkoff/invest/grpc/orders_pb2_grpc.py
tinkoff_investments-0.2.0b116.dist-info/LICENSE
tinkoff_investments-0.2.0b116.dist-info/METADATA
tinkoff_investments-0.2.0b116.dist-info/WHEEL
tinkoff_investments-0.2.0b116.dist-info/RECORD
