Metadata-Version: 2.1
Name: tinkoff-investments
Version: 0.2.0b116
Summary: Tinkoff Python SDK
Home-page: https://github.com/RussianInvestments/invest-python
License: Apache-2.0
Author: Tinkoff Team
Author-email: python@tinkoff.ru
Requires-Python: >=3.8.1,<4.0.0
Classifier: License :: OSI Approved :: Apache Software License
Classifier: Programming Language :: Python :: 3
Classifier: Programming Language :: Python :: 3.9
Classifier: Programming Language :: Python :: 3.10
Classifier: Programming Language :: Python :: 3.11
Classifier: Programming Language :: Python :: 3.12
Provides-Extra: all
Requires-Dist: cachetools (>=5.2.0,<6.0.0)
Requires-Dist: deprecation (>=2.1.0,<3.0.0)
Requires-Dist: grpcio (>=1.59.3,<2.0.0)
Requires-Dist: matplotlib (>=3.5.1,<4.0.0) ; extra == "all"
Requires-Dist: mplfinance (>=0.12.8-beta.9,<0.13.0) ; extra == "all"
Requires-Dist: numpy (>=1.22.2,<2.0.0) ; extra == "all"
Requires-Dist: pandas (>=1.4.0) ; extra == "all"
Requires-Dist: protobuf (>=4.25.1,<5.0.0)
Requires-Dist: python-dateutil (>=2.8.2,<3.0.0)
Requires-Dist: tinkoff (>=0.1.1,<0.2.0)
Project-URL: Repository, https://github.com/RussianInvestments/invest-python
